adorable_cli/__init__.py
adorable_cli/__main__.py
adorable_cli/config.py
adorable_cli/console.py
adorable_cli/main.py
adorable_cli/settings.py
adorable_cli/agent/builder.py
adorable_cli/agent/main_agent.py
adorable_cli/agent/patches.py
adorable_cli/agent/policy.py
adorable_cli/agent/prompts.py
adorable_cli/context/__init__.py
adorable_cli/context/agent_context.py
adorable_cli/context/assembler.py
adorable_cli/context/normalizer.py
adorable_cli/core/__init__.py
adorable_cli/core/anr_detector.py
adorable_cli/core/loop.py
adorable_cli/db/__init__.py
adorable_cli/db/migrations.py
adorable_cli/ext/__init__.py
adorable_cli/ext/_python_loader.py
adorable_cli/ext/commands.py
adorable_cli/ext/skills.py
adorable_cli/ext/tools.py
adorable_cli/knowledge/__init__.py
adorable_cli/knowledge/manager.py
adorable_cli/memory/__init__.py
adorable_cli/memory/compression.py
adorable_cli/memory/summarizer.py
adorable_cli/memory/working_memory.py
adorable_cli/models/__init__.py
adorable_cli/models/events.py
adorable_cli/models/messages.py
adorable_cli/os/__init__.py
adorable_cli/os/remote_agent.py
adorable_cli/os/server.py
adorable_cli/prompts/__init__.py
adorable_cli/prompts/engineering.py
adorable_cli/prompts/psychological.py
adorable_cli/prompts/templates.py
adorable_cli/tools/__init__.py
adorable_cli/tools/agent_tool.py
adorable_cli/tools/bash_sandbox.py
adorable_cli/tools/executor.py
adorable_cli/tools/file_safety.py
adorable_cli/tools/todo_tools.py
adorable_cli/tools/vision_tool.py
adorable_cli/ui/enhanced_input.py
adorable_cli/ui/interactive.py
adorable_cli/ui/stream_renderer.py
adorable_cli/ui/utils.py
adorable_cli/utils/__init__.py
adorable_cli/utils/backpressure.py
adorable_cli/utils/errors.py
adorable_cli/utils/streaming_json.py
adorable_cli/workflows/__init__.py
adorable_cli/workflows/registry.py
adorable_cli-0.2.18.dist-info/licenses/LICENSE
adorable_cli-0.2.18.dist-info/METADATA
adorable_cli-0.2.18.dist-info/WHEEL
adorable_cli-0.2.18.dist-info/entry_points.txt
adorable_cli-0.2.18.dist-info/top_level.txt
adorable_cli-0.2.18.dist-info/RECORD
