Metadata-Version: 2.4
Name: adorable-cli
Version: 0.2.18
Summary: A powerful CLI super agent
Author-email: LeonEthan <czlbou2012@gmail.com>
License-Expression: MIT
Requires-Python: >=3.10
License-File: LICENSE
Requires-Dist: agno>=2.2.8
Requires-Dist: fastapi>=0.110.0
Requires-Dist: rich>=13.0.0
Requires-Dist: typer>=0.12.0
Requires-Dist: openai>=1.0.0
Requires-Dist: pyyaml>=6.0.0
Requires-Dist: ddgs<9.6.0
Requires-Dist: firecrawl-py>=4.3.6
Requires-Dist: httpx[socks]>=0.28.1
Requires-Dist: chonkie>=1.3.1
Requires-Dist: mcp>=1.17.0
Requires-Dist: sqlalchemy>=2.0.44
Requires-Dist: prompt-toolkit>=3.0.0
Requires-Dist: update>=0.0.1
Requires-Dist: uvicorn>=0.30.0
Requires-Dist: lancedb>=0.17.0
Requires-Dist: pandas>=2.0.0
Provides-Extra: dev
Requires-Dist: pytest>=8.0.0; extra == "dev"
Requires-Dist: pytest-asyncio>=0.23.0; extra == "dev"
Dynamic: license-file
